swift_cloud_py/__init__.py
swift_cloud_py/enums.py
swift_cloud_py/swift_cloud_api.py
swift_cloud_py/authentication/__init__.py
swift_cloud_py/authentication/authentication.py
swift_cloud_py/authentication/check_internet_connection.py
swift_cloud_py/authentication/credentials.py
swift_cloud_py/common/__init__.py
swift_cloud_py/common/errors.py
swift_cloud_py/entities/__init__.py
swift_cloud_py/entities/control_output/__init__.py
swift_cloud_py/entities/control_output/fixed_time_schedule.py
swift_cloud_py/entities/control_output/phase_diagram.py
swift_cloud_py/entities/control_output/test/__init__.py
swift_cloud_py/entities/control_output/test/test_fixed_time_schedule.py
swift_cloud_py/entities/control_output/test/test_phase_diagram.py
swift_cloud_py/entities/intersection/__init__.py
swift_cloud_py/entities/intersection/intersection.py
swift_cloud_py/entities/intersection/periodic_order.py
swift_cloud_py/entities/intersection/sg_relations.py
swift_cloud_py/entities/intersection/signalgroup.py
swift_cloud_py/entities/intersection/traffic_light.py
swift_cloud_py/entities/intersection/test/__init__.py
swift_cloud_py/entities/intersection/test/test_intersection.py
swift_cloud_py/entities/intersection/test/test_periodic_order.py
swift_cloud_py/entities/intersection/test/test_sg_relations.py
swift_cloud_py/entities/intersection/test/test_signalgroup.py
swift_cloud_py/entities/intersection/test/test_traffic_light.py
swift_cloud_py/entities/kpis/__init__.py
swift_cloud_py/entities/kpis/kpis.py
swift_cloud_py/entities/scenario/__init__.py
swift_cloud_py/entities/scenario/arrival_rates.py
swift_cloud_py/entities/scenario/queue_lengths.py
swift_cloud_py/entities/scenario/test/__init__.py
swift_cloud_py/entities/scenario/test/test_arrival_rates.py
swift_cloud_py/entities/scenario/test/test_queue_lengths.py
swift_cloud_py/examples/__init__.py
swift_cloud_py/examples/create_intersection.py
swift_cloud_py/examples/evaluate_fixed_time_schedule.py
swift_cloud_api-0.14.0.dist-info/LICENSE
swift_cloud_api-0.14.0.dist-info/METADATA
swift_cloud_api-0.14.0.dist-info/WHEEL
swift_cloud_api-0.14.0.dist-info/top_level.txt
swift_cloud_api-0.14.0.dist-info/RECORD
