Metadata-Version: 2.1
Name: swift-cloud-api
Version: 0.14.0
Summary: Swift Mobility Cloud API Interface
Home-page: https://github.com/stijnfleuren/SwiftCloudApi
Author: S.T.G. Fleuren
Author-email: stijn.fleuren@swiftmobility.eu
License: UNKNOWN
Platform: UNKNOWN
Classifier: Programming Language :: Python :: 3
Classifier: License :: OSI Approved :: MIT License
Classifier: Operating System :: OS Independent
Requires-Python: >=3.7
License-File: LICENSE
Requires-Dist: requests
